[{"id":"77697","title":"Bella Vista","price":424,"currency":"EUR","country":"Egypte","departure":"","departureDate":"2026-01-21","duration":8,"stars":3,"province":"","region":"Hurghada","serviceType":"AI","url":"https://reis.tui.nl/c?c=433&m=1564650&a=453979&r=hackerdeal2.0&u=https%3A%2F%2Fwww.tui.nl%2Fbella-vista-50977697%2F%3FDepartureDate%3D2026-01-21%26Duration%3D8%26TransportType%3D2","banner":"https://media.tuicontent.nl/C87/C873AD3705096ECBE8DF1A89CA49495A.jpg"},{"id":"557055","title":"Sindbad Club","price":478,"currency":"EUR","country":"Egypte","departure":"","departureDate":"2026-01-21","duration":8,"stars":4,"province":"","region":"Hurghada","serviceType":"AI","url":"https://reis.tui.nl/c?c=433&m=1564650&a=453979&r=hackerdeal2.0&u=https%3A%2F%2Fwww.tui.nl%2Fsindbad-club-509557055%2F%3FDepartureDate%3D2026-01-21%26Duration%3D8%26TransportType%3D2","banner":"https://media.tuicontent.nl/7E7/7E7ADCE688DA9D66ABDE5E40AA949DAC.jpg"},{"id":"662440","title":"Casa Mare Resort","price":486,"currency":"EUR","country":"Egypte","departure":"","departureDate":"2026-01-21","duration":8,"stars":4,"province":"","region":"Marsa Alam","serviceType":"AI","url":"https://reis.tui.nl/c?c=433&m=1564650&a=453979&r=hackerdeal2.0&u=https%3A%2F%2Fwww.tui.nl%2Fcasa-mare-resort-509662440%2F%3FDepartureDate%3D2026-01-21%26Duration%3D8%26TransportType%3D2","banner":"https://media.tuicontent.nl/093/093686AA08E11BF445C6E91AC800E519.jpg"},{"id":"36875","title":"Falcon Hills","price":487,"currency":"EUR","country":"Egypte","departure":"","departureDate":"2026-06-12","duration":8,"stars":3,"province":"","region":"Sharm el Sheikh","serviceType":"AI","url":"https://reis.tui.nl/c?c=433&m=1564650&a=453979&r=hackerdeal2.0&u=https%3A%2F%2Fwww.tui.nl%2Ffalcon-hills-50936875%2F%3FDepartureDate%3D2026-06-12%26Duration%3D8%26TransportType%3D2","banner":"https://media.tuicontent.nl/683/683F0ECF1C24A1C692A3C7A957E74F5A.jpg"},{"id":"49031","title":"Ali Baba","price":495,"currency":"EUR","country":"Egypte","departure":"","departureDate":"2026-01-21","duration":8,"stars":4,"province":"","region":"Hurghada","serviceType":"AI","url":"https://reis.tui.nl/c?c=433&m=1564650&a=453979&r=hackerdeal2.0&u=https%3A%2F%2Fwww.tui.nl%2Fali-baba-50949031%2F%3FDepartureDate%3D2026-01-21%26Duration%3D8%26TransportType%3D2","banner":"https://media.tuicontent.nl/205/20576DFB4D1B67566A849687C2ADF09F.jpg"},{"id":"292136","title":"Serenity Alma Heights","price":501,"currency":"EUR","country":"Egypte","departure":"","departureDate":"2026-01-21","duration":8,"stars":5,"province":"","region":"Hurghada","serviceType":"AI","url":"https://reis.tui.nl/c?c=433&m=1564650&a=453979&r=hackerdeal2.0&u=https%3A%2F%2Fwww.tui.nl%2Fserenity-alma-heights-509292136%2F%3FDepartureDate%3D2026-01-21%26Duration%3D8%26TransportType%3D2","banner":"https://media.tuicontent.nl/DAA/DAAD274EE2930CEC0F2DCEFBF6E224BB.jpg"},{"id":"933950","title":"Flamenco Beach Resort","price":504,"currency":"EUR","country":"Egypte","departure":"","departureDate":"2026-01-21","duration":8,"stars":4,"province":"","region":"Marsa Alam","serviceType":"AI","url":"https://reis.tui.nl/c?c=433&m=1564650&a=453979&r=hackerdeal2.0&u=https%3A%2F%2Fwww.tui.nl%2Fflamenco-beach-resort-509933950%2F%3FDepartureDate%3D2026-01-21%26Duration%3D8%26TransportType%3D2","banner":"https://media.tuicontent.nl/5E3/5E37AFD09111EB8319FA6215AA6793DB.jpg"},{"id":"51421","title":"Brayka Bay Resort","price":511,"currency":"EUR","country":"Egypte","departure":"","departureDate":"2026-01-21","duration":8,"stars":4,"province":"","region":"Marsa Alam","serviceType":"AI","url":"https://reis.tui.nl/c?c=433&m=1564650&a=453979&r=hackerdeal2.0&u=https%3A%2F%2Fwww.tui.nl%2Fbrayka-bay-resort-50951421%2F%3FDepartureDate%3D2026-01-21%26Duration%3D8%26TransportType%3D2","banner":"https://media.tuicontent.nl/F42/F422812F6B53763B98A135C2E06B4429.jpg"},{"id":"493987","title":"Concorde Moreen Beach & Spa","price":517,"currency":"EUR","country":"Egypte","departure":"","departureDate":"2026-01-21","duration":8,"stars":5,"province":"","region":"Marsa Alam","serviceType":"AI","url":"https://reis.tui.nl/c?c=433&m=1564650&a=453979&r=hackerdeal2.0&u=https%3A%2F%2Fwww.tui.nl%2Fconcorde-moreen-beach-en-spa-509493987%2F%3FDepartureDate%3D2026-01-21%26Duration%3D8%26TransportType%3D2","banner":"https://media.tuicontent.nl/4F7/4F7C1DDAC3DFA7F1EA0352621EC23A58.jpg"},{"id":"30111","title":"Arabia Azur Beach","price":529,"currency":"EUR","country":"Egypte","departure":"","departureDate":"2026-01-21","duration":8,"stars":3,"province":"","region":"Hurghada","serviceType":"AI","url":"https://reis.tui.nl/c?c=433&m=1564650&a=453979&r=hackerdeal2.0&u=https%3A%2F%2Fwww.tui.nl%2Farabia-azur-beach-50930111%2F%3FDepartureDate%3D2026-01-21%26Duration%3D8%26TransportType%3D2","banner":"https://media.tuicontent.nl/BCB/BCB300EE86E68C571B5E18631C25F756.jpg"},{"id":"655111","title":"Jaz Soma Beach","price":556,"currency":"EUR","country":"Egypte","departure":"","departureDate":"2026-01-21","duration":8,"stars":4,"province":"","region":"Hurghada","serviceType":"AI","url":"https://reis.tui.nl/c?c=433&m=1564650&a=453979&r=hackerdeal2.0&u=https%3A%2F%2Fwww.tui.nl%2Fjaz-soma-beach-509655111%2F%3FDepartureDate%3D2026-01-21%26Duration%3D8%26TransportType%3D2","banner":"https://media.tuicontent.nl/E01/E01CD4432C342CF330D97B836C66B196.jpg"},{"id":"509956","title":"Akassia Swiss Resort","price":562,"currency":"EUR","country":"Egypte","departure":"","departureDate":"2026-01-21","duration":8,"stars":4,"province":"","region":"Marsa Alam","serviceType":"AI","url":"https://reis.tui.nl/c?c=433&m=1564650&a=453979&r=hackerdeal2.0&u=https%3A%2F%2Fwww.tui.nl%2Fakassia-swiss-resort-509509956%2F%3FDepartureDate%3D2026-01-21%26Duration%3D8%26TransportType%3D2","banner":"https://media.tuicontent.nl/B81/B8183C402B5929611FB3DEB89C29220D.jpg"},{"id":"332573","title":"Tropitel Sahl Hasheesh","price":599,"currency":"EUR","country":"Egypte","departure":"","departureDate":"2026-01-21","duration":8,"stars":5,"province":"","region":"Hurghada","serviceType":"AI","url":"https://reis.tui.nl/c?c=433&m=1564650&a=453979&r=hackerdeal2.0&u=https%3A%2F%2Fwww.tui.nl%2Ftropitel-sahl-hasheesh-509332573%2F%3FDepartureDate%3D2026-01-21%26Duration%3D8%26TransportType%3D2","banner":"https://media.tuicontent.nl/3F7/3F7F500C1FB7A717BFC2D57E0C60A884.jpg"},{"id":"78317","title":"Pickalbatros Jungle Aqua Park Resort Neverland","price":609,"currency":"EUR","country":"Egypte","departure":"","departureDate":"2026-01-26","duration":8,"stars":4,"province":"","region":"Hurghada","serviceType":"AI","url":"https://reis.tui.nl/c?c=433&m=1564650&a=453979&r=hackerdeal2.0&u=https%3A%2F%2Fwww.tui.nl%2Fpickalbatros-jungle-aqua-park-resort-neverland-50978317%2F%3FDepartureDate%3D2026-01-26%26Duration%3D8%26TransportType%3D2","banner":"https://media.tuicontent.nl/CDB/CDB45AB5C8015DACC3378CEB5533431C.jpg"},{"id":"77695","title":"Pickalbatros Palace Resort","price":634,"currency":"EUR","country":"Egypte","departure":"","departureDate":"2026-01-14","duration":8,"stars":5,"province":"","region":"Hurghada","serviceType":"AI","url":"https://reis.tui.nl/c?c=433&m=1564650&a=453979&r=hackerdeal2.0&u=https%3A%2F%2Fwww.tui.nl%2Fpickalbatros-palace-resort-50977695%2F%3FDepartureDate%3D2026-01-14%26Duration%3D8%26TransportType%3D2","banner":"https://media.tuicontent.nl/EDC/EDCA83CC714418CEEEAA3A7B9628F836.jpg"},{"id":"332574","title":"Stella di Mare Beach Hotel & Spa","price":634,"currency":"EUR","country":"Egypte","departure":"","departureDate":"2026-01-21","duration":8,"stars":5,"province":"","region":"Sharm el Sheikh","serviceType":"HP","url":"https://reis.tui.nl/c?c=433&m=1564650&a=453979&r=hackerdeal2.0&u=https%3A%2F%2Fwww.tui.nl%2Fstella-di-mare-beach-hotel-en-spa-509332574%2F%3FDepartureDate%3D2026-01-21%26Duration%3D8%26TransportType%3D2","banner":"https://media.tuicontent.nl/4CE/4CEEAAD1F0707420A8C702F335D12599.jpg"},{"id":"57780","title":"Jaz Mirabel Beach Resort","price":636,"currency":"EUR","country":"Egypte","departure":"","departureDate":"2026-01-21","duration":8,"stars":5,"province":"","region":"Sharm el Sheikh","serviceType":"AI","url":"https://reis.tui.nl/c?c=433&m=1564650&a=453979&r=hackerdeal2.0&u=https%3A%2F%2Fwww.tui.nl%2Fjaz-mirabel-beach-resort-50957780%2F%3FDepartureDate%3D2026-01-21%26Duration%3D8%26TransportType%3D2","banner":"https://media.tuicontent.nl/8D4/8D4DA5AB1390E434E6B09B77A3303F1B.jpg"},{"id":"77696","title":"Jaz Aquamarine Resort","price":638,"currency":"EUR","country":"Egypte","departure":"","departureDate":"2026-01-21","duration":8,"stars":5,"province":"","region":"Hurghada","serviceType":"AI","url":"https://reis.tui.nl/c?c=433&m=1564650&a=453979&r=hackerdeal2.0&u=https%3A%2F%2Fwww.tui.nl%2Fjaz-aquamarine-resort-50977696%2F%3FDepartureDate%3D2026-01-21%26Duration%3D8%26TransportType%3D2","banner":"https://media.tuicontent.nl/75A/75A2686BF3689F1A50738B3A15FFA66C.jpg"},{"id":"78447","title":"Coral Sea Holiday Resort","price":639,"currency":"EUR","country":"Egypte","departure":"","departureDate":"2026-01-21","duration":8,"stars":5,"province":"","region":"Sharm el Sheikh","serviceType":"AI","url":"https://reis.tui.nl/c?c=433&m=1564650&a=453979&r=hackerdeal2.0&u=https%3A%2F%2Fwww.tui.nl%2Fcoral-sea-holiday-resort-50978447%2F%3FDepartureDate%3D2026-01-21%26Duration%3D8%26TransportType%3D2","banner":"https://media.tuicontent.nl/DE7/DE7A35E8E3B142F094DD70111A41F39E.jpg"},{"id":"49082","title":"SPLASHWORLD Jaz Lamaya","price":640,"currency":"EUR","country":"Egypte","departure":"","departureDate":"2026-01-21","duration":8,"stars":5,"province":"","region":"Marsa Alam","serviceType":"AI","url":"https://reis.tui.nl/c?c=433&m=1564650&a=453979&r=hackerdeal2.0&u=https%3A%2F%2Fwww.tui.nl%2Fsplashworld-jaz-lamaya-50949082%2F%3FDepartureDate%3D2026-01-21%26Duration%3D8%26TransportType%3D2","banner":"https://media.tuicontent.nl/C38/C3877635A0F6D62517E3B5E931CCC047.jpg"},{"id":"147995","title":"Jaz Grand Marsa","price":648,"currency":"EUR","country":"Egypte","departure":"","departureDate":"2026-01-21","duration":8,"stars":5,"province":"","region":"Marsa Alam","serviceType":"AI","url":"https://reis.tui.nl/c?c=433&m=1564650&a=453979&r=hackerdeal2.0&u=https%3A%2F%2Fwww.tui.nl%2Fjaz-grand-marsa-509147995%2F%3FDepartureDate%3D2026-01-21%26Duration%3D8%26TransportType%3D2","banner":"https://media.tuicontent.nl/3A1/3A1BBD793E096463E52E89A44C2BA3C8.jpg"},{"id":"49276","title":"Pickalbatros Royal Moderna","price":648,"currency":"EUR","country":"Egypte","departure":"","departureDate":"2026-01-21","duration":8,"stars":5,"province":"","region":"Sharm el Sheikh","serviceType":"AI","url":"https://reis.tui.nl/c?c=433&m=1564650&a=453979&r=hackerdeal2.0&u=https%3A%2F%2Fwww.tui.nl%2Fpickalbatros-royal-moderna-50949276%2F%3FDepartureDate%3D2026-01-21%26Duration%3D8%26TransportType%3D2","banner":"https://media.tuicontent.nl/D1B/D1B9699BC8A2A0E9D8F8217197428151.jpg"},{"id":"375686","title":"Hilton Marsa Alam Nubian Resort","price":654,"currency":"EUR","country":"Egypte","departure":"","departureDate":"2026-01-14","duration":8,"stars":4,"province":"","region":"Marsa Alam","serviceType":"AI","url":"https://reis.tui.nl/c?c=433&m=1564650&a=453979&r=hackerdeal2.0&u=https%3A%2F%2Fwww.tui.nl%2Fhilton-marsa-alam-nubian-resort-509375686%2F%3FDepartureDate%3D2026-01-14%26Duration%3D8%26TransportType%3D2","banner":"https://media.tuicontent.nl/839/83901B5B0302C98BFE77E494A99ABA05.jpg"},{"id":"933854","title":"SENTIDO Mamlouk Palace","price":660,"currency":"EUR","country":"Egypte","departure":"","departureDate":"2026-02-05","duration":8,"stars":5,"province":"","region":"Hurghada","serviceType":"LO","url":"https://reis.tui.nl/c?c=433&m=1564650&a=453979&r=hackerdeal2.0&u=https%3A%2F%2Fwww.tui.nl%2Fsentido-mamlouk-palace-509933854%2F%3FDepartureDate%3D2026-02-05%26Duration%3D8%26TransportType%3D2","banner":"https://media.tuicontent.nl/06F/06F4772B6A1255C333A612262B5BC3A3.jpg"},{"id":"668819","title":"Iberotel Casa del Mar Resort","price":664,"currency":"EUR","country":"Egypte","departure":"","departureDate":"2026-01-28","duration":8,"stars":4,"province":"","region":"Hurghada","serviceType":"AI","url":"https://reis.tui.nl/c?c=433&m=1564650&a=453979&r=hackerdeal2.0&u=https%3A%2F%2Fwww.tui.nl%2Fiberotel-casa-del-mar-resort-509668819%2F%3FDepartureDate%3D2026-01-28%26Duration%3D8%26TransportType%3D2","banner":"https://media.tuicontent.nl/4C5/4C52190F2B92987555C4E06D3268775E.jpg"},{"id":"49072","title":"Pickalbatros Dana Beach Resort","price":667,"currency":"EUR","country":"Egypte","departure":"","departureDate":"2026-01-14","duration":8,"stars":5,"province":"","region":"Hurghada","serviceType":"AI","url":"https://reis.tui.nl/c?c=433&m=1564650&a=453979&r=hackerdeal2.0&u=https%3A%2F%2Fwww.tui.nl%2Fpickalbatros-dana-beach-resort-50949072%2F%3FDepartureDate%3D2026-01-14%26Duration%3D8%26TransportType%3D2","banner":"https://media.tuicontent.nl/1B0/1B0F900FBF4B74A79A68B058BD8EB984.jpg"},{"id":"433286","title":"Jaz Bluemarine","price":669,"currency":"EUR","country":"Egypte","departure":"","departureDate":"2026-01-21","duration":8,"stars":5,"province":"","region":"Hurghada","serviceType":"AI","url":"https://reis.tui.nl/c?c=433&m=1564650&a=453979&r=hackerdeal2.0&u=https%3A%2F%2Fwww.tui.nl%2Fjaz-bluemarine-509433286%2F%3FDepartureDate%3D2026-01-21%26Duration%3D8%26TransportType%3D2","banner":"https://media.tuicontent.nl/5B4/5B4F5F5C4948C73EADDED57976EC9969.jpg"},{"id":"75654","title":"Jaz Neo Dar El Madina","price":677,"currency":"EUR","country":"Egypte","departure":"","departureDate":"2026-01-17","duration":8,"stars":4,"province":"","region":"Marsa Alam","serviceType":"AI","url":"https://reis.tui.nl/c?c=433&m=1564650&a=453979&r=hackerdeal2.0&u=https%3A%2F%2Fwww.tui.nl%2Fjaz-neo-dar-el-madina-50975654%2F%3FDepartureDate%3D2026-01-17%26Duration%3D8%26TransportType%3D2","banner":"https://media.tuicontent.nl/481/4811CD98257ABCA7B881A23C4F0DCD0B.jpg"},{"id":"78451","title":"SPLASHWORLD Coral Sea Waterworld","price":688,"currency":"EUR","country":"Egypte","departure":"","departureDate":"2026-01-21","duration":8,"stars":4,"province":"","region":"Sharm el Sheikh","serviceType":"AI","url":"https://reis.tui.nl/c?c=433&m=1564650&a=453979&r=hackerdeal2.0&u=https%3A%2F%2Fwww.tui.nl%2Fsplashworld-coral-sea-waterworld-50978451%2F%3FDepartureDate%3D2026-01-21%26Duration%3D8%26TransportType%3D2","banner":"https://media.tuicontent.nl/7CC/7CC4C669844BF6A8A4D7B9B9E6DC9ECC.jpg"},{"id":"784824","title":"TUI MAGIC LIFE Redsina Sharm el Sheikh","price":689,"currency":"EUR","country":"Egypte","departure":"","departureDate":"2026-01-24","duration":8,"stars":5,"province":"","region":"Sharm el Sheikh","serviceType":"AI","url":"https://reis.tui.nl/c?c=433&m=1564650&a=453979&r=hackerdeal2.0&u=https%3A%2F%2Fwww.tui.nl%2Ftui-magic-life-redsina-sharm-el-sheikh-509784824%2F%3FDepartureDate%3D2026-01-24%26Duration%3D8%26TransportType%3D2","banner":"https://media.tuicontent.nl/105/105B464279E118CCA9E235DB69442334.jpg"},{"id":"696086","title":"SUNRISE Garden Beach Resort Select","price":704,"currency":"EUR","country":"Egypte","departure":"","departureDate":"2026-01-26","duration":8,"stars":5,"province":"","region":"Hurghada","serviceType":"AI","url":"https://reis.tui.nl/c?c=433&m=1564650&a=453979&r=hackerdeal2.0&u=https%3A%2F%2Fwww.tui.nl%2Fsunrise-garden-beach-resort-select--509696086%2F%3FDepartureDate%3D2026-01-26%26Duration%3D8%26TransportType%3D2","banner":"https://media.tuicontent.nl/C16/C16B4A6B332F0026FEF0E381FBE113DA.jpg"},{"id":"71758","title":"TUI MAGIC LIFE Kalawy","price":713,"currency":"EUR","country":"Egypte","departure":"","departureDate":"2026-01-21","duration":8,"stars":5,"province":"","region":"Hurghada","serviceType":"AI","url":"https://reis.tui.nl/c?c=433&m=1564650&a=453979&r=hackerdeal2.0&u=https%3A%2F%2Fwww.tui.nl%2Ftui-magic-life-kalawy-50971758%2F%3FDepartureDate%3D2026-01-21%26Duration%3D8%26TransportType%3D2","banner":"https://media.tuicontent.nl/54B/54BDBE9057D1E5DEEE5987B63B2892AE.jpg"},{"id":"483806","title":"Xperience Seabreeze","price":718,"currency":"EUR","country":"Egypte","departure":"","departureDate":"2026-06-12","duration":8,"stars":4,"province":"","region":"Sharm el Sheikh","serviceType":"AI","url":"https://reis.tui.nl/c?c=433&m=1564650&a=453979&r=hackerdeal2.0&u=https%3A%2F%2Fwww.tui.nl%2Fxperience-seabreeze-509483806%2F%3FDepartureDate%3D2026-06-12%26Duration%3D8%26TransportType%3D2","banner":"https://media.tuicontent.nl/65F/65F0E19D7193618615E8EE827AF6217A.jpg"},{"id":"932840","title":"Royal Star Beach Resort","price":757,"currency":"EUR","country":"Egypte","departure":"","departureDate":"2026-03-19","duration":8,"stars":4,"province":"","region":"Hurghada","serviceType":"AI","url":"https://reis.tui.nl/c?c=433&m=1564650&a=453979&r=hackerdeal2.0&u=https%3A%2F%2Fwww.tui.nl%2Froyal-star-beach-resort-509932840%2F%3FDepartureDate%3D2026-03-19%26Duration%3D8%26TransportType%3D2","banner":"https://media.tuicontent.nl/5DA/5DA8CC3456F180AE5F134AB1D024DFA0.jpg"},{"id":"933534","title":"Golden Beach Hurghada","price":760,"currency":"EUR","country":"Egypte","departure":"","departureDate":"2026-06-22","duration":8,"stars":4,"province":"","region":"Hurghada","serviceType":"AI","url":"https://reis.tui.nl/c?c=433&m=1564650&a=453979&r=hackerdeal2.0&u=https%3A%2F%2Fwww.tui.nl%2Fgolden-beach-hurghada-509933534%2F%3FDepartureDate%3D2026-06-22%26Duration%3D8%26TransportType%3D2","banner":"https://media.tuicontent.nl/512/512CBB110FF5DC87E43E694847E0BDF4.jpg"},{"id":"14201","title":"Arabella Azur","price":785,"currency":"EUR","country":"Egypte","departure":"","departureDate":"2026-06-22","duration":8,"stars":3,"province":"","region":"Hurghada","serviceType":"AI","url":"https://reis.tui.nl/c?c=433&m=1564650&a=453979&r=hackerdeal2.0&u=https%3A%2F%2Fwww.tui.nl%2Farabella-azur-50914201%2F%3FDepartureDate%3D2026-06-22%26Duration%3D8%26TransportType%3D2","banner":"https://media.tuicontent.nl/9C7/9C72EBE80C45DA43A7E05D4319173FE9.jpg"}]