[{"id":"557139","title":"Tia Apart","price":337,"currency":"EUR","country":"Oostenrijk","departure":"","departureDate":"2026-09-27","duration":4,"stars":"3","province":"","region":"Kaunertaler Gletscher","serviceType":"LG","url":"https://reis.tui.nl/c?c=433&m=1564650&a=453979&r=hackerdeal2.0&u=https%3A%2F%2Fwww.tui.nl%2Ftia-apart-509557139%2F%3FDepartureDate%3D2026-09-27%26Duration%3D4%26TransportType%3D2","banner":"https://media.tuicontent.nl/517/517F365B8FBA833F5D97CAFA16AACDFD.jpg"},{"id":"980127","title":"Bergresort Tauernblick by Alps Resorts","price":368,"currency":"EUR","country":"Oostenrijk","departure":"","departureDate":"2026-10-01","duration":4,"stars":"","province":"","region":"Kitzbühel Kirchberg","serviceType":"LG","url":"https://reis.tui.nl/c?c=433&m=1564650&a=453979&r=hackerdeal2.0&u=https%3A%2F%2Fwww.tui.nl%2Fbergresort-tauernblick-by-alps-resorts-509980127%2F%3FDepartureDate%3D2026-10-01%26Duration%3D4%26TransportType%3D2","banner":"https://media.tuicontent.nl/ECD/ECD0105FE1BDD0FE4CD577C228DC1723.jpg"},{"id":"175765","title":"Wasserfall","price":400,"currency":"EUR","country":"Oostenrijk","departure":"","departureDate":"2026-10-01","duration":4,"stars":"3","province":"","region":"Salzburgerland","serviceType":"VP","url":"https://reis.tui.nl/c?c=433&m=1564650&a=453979&r=hackerdeal2.0&u=https%3A%2F%2Fwww.tui.nl%2Fwasserfall-509175765%2F%3FDepartureDate%3D2026-10-01%26Duration%3D4%26TransportType%3D2","banner":"https://media.tuicontent.nl/C20/C202DC09E6C0D62752FED48D53BAAEDB.jpg"},{"id":"15512","title":"Staudacher","price":401,"currency":"EUR","country":"Oostenrijk","departure":"","departureDate":"2026-09-16","duration":4,"stars":"3","province":"","region":"Tirol","serviceType":"LG","url":"https://reis.tui.nl/c?c=433&m=1564650&a=453979&r=hackerdeal2.0&u=https%3A%2F%2Fwww.tui.nl%2Fstaudacher-50915512%2F%3FDepartureDate%3D2026-09-16%26Duration%3D4%26TransportType%3D2","banner":"https://media.tuicontent.nl/416/4166E51F36C2B070291F78641708EE82.jpg"},{"id":"683643","title":"Carpe Solem","price":403,"currency":"EUR","country":"Oostenrijk","departure":"","departureDate":"2026-05-07","duration":4,"stars":"4","province":"","region":"Fanningberg","serviceType":"LG","url":"https://reis.tui.nl/c?c=433&m=1564650&a=453979&r=hackerdeal2.0&u=https%3A%2F%2Fwww.tui.nl%2Fcarpe-solem-509683643%2F%3FDepartureDate%3D2026-05-07%26Duration%3D4%26TransportType%3D2","banner":"https://media.tuicontent.nl/7AF/7AF53C7A78082BAB8F1AEC1163B1D47C.jpg"},{"id":"767946","title":"Tauernresidence Radstadt","price":409,"currency":"EUR","country":"Oostenrijk","departure":"","departureDate":"2026-05-07","duration":4,"stars":"","province":"","region":"Salzburger Sportwelt","serviceType":"LG","url":"https://reis.tui.nl/c?c=433&m=1564650&a=453979&r=hackerdeal2.0&u=https%3A%2F%2Fwww.tui.nl%2Ftauernresidence-radstadt-509767946%2F%3FDepartureDate%3D2026-05-07%26Duration%3D4%26TransportType%3D2","banner":"https://media.tuicontent.nl/E53/E53CED0FF9FB001F5D97E41AEBEC618E.jpg"},{"id":"781363","title":"Pension Tirol","price":411,"currency":"EUR","country":"Oostenrijk","departure":"","departureDate":"2026-05-27","duration":4,"stars":"3","province":"","region":"Oberinntal","serviceType":"LO","url":"https://reis.tui.nl/c?c=433&m=1564650&a=453979&r=hackerdeal2.0&u=https%3A%2F%2Fwww.tui.nl%2Fpension-tirol-509781363%2F%3FDepartureDate%3D2026-05-27%26Duration%3D4%26TransportType%3D2","banner":"https://media.tuicontent.nl/797/79712D357FDE69408C2A680F458D8707.jpg"},{"id":"183869","title":"Tia Monte","price":411,"currency":"EUR","country":"Oostenrijk","departure":"","departureDate":"2026-09-23","duration":4,"stars":"3","province":"","region":"Kaunertaler Gletscher","serviceType":"HP","url":"https://reis.tui.nl/c?c=433&m=1564650&a=453979&r=hackerdeal2.0&u=https%3A%2F%2Fwww.tui.nl%2Ftia-monte-509183869%2F%3FDepartureDate%3D2026-09-23%26Duration%3D4%26TransportType%3D2","banner":"https://media.tuicontent.nl/F77/F77250E2C21396ACD894535102936D82.jpg"},{"id":"545299","title":"Aparthotel AlpenChalet","price":431,"currency":"EUR","country":"Oostenrijk","departure":"","departureDate":"2026-10-01","duration":4,"stars":"4","province":"","region":"Salzburgerland","serviceType":"LO","url":"https://reis.tui.nl/c?c=433&m=1564650&a=453979&r=hackerdeal2.0&u=https%3A%2F%2Fwww.tui.nl%2Faparthotel-alpenchalet-509545299%2F%3FDepartureDate%3D2026-10-01%26Duration%3D4%26TransportType%3D2","banner":"https://media.tuicontent.nl/725/725BD95375E07DBC98BD8F2543AC28A6.jpg"},{"id":"773385","title":"Mozart","price":434,"currency":"EUR","country":"Oostenrijk","departure":"","departureDate":"2026-06-13","duration":4,"stars":"3","province":"","region":"Wenen","serviceType":"LO","url":"https://reis.tui.nl/c?c=433&m=1564650&a=453979&r=hackerdeal2.0&u=https%3A%2F%2Fwww.tui.nl%2Fmozart-509773385%2F%3FDepartureDate%3D2026-06-13%26Duration%3D4%26TransportType%3D2","banner":"https://media.tuicontent.nl/87B/87B4D88814992BF429C2011BF86D8D4E.jpg"},{"id":"47343","title":"Boltzmann","price":444,"currency":"EUR","country":"Oostenrijk","departure":"","departureDate":"2026-08-28","duration":4,"stars":"3","province":"","region":"Wenen","serviceType":"LO","url":"https://reis.tui.nl/c?c=433&m=1564650&a=453979&r=hackerdeal2.0&u=https%3A%2F%2Fwww.tui.nl%2Fboltzmann-50947343%2F%3FDepartureDate%3D2026-08-28%26Duration%3D4%26TransportType%3D2","banner":"https://media.tuicontent.nl/349/3495397C464B9EF3018356C50F018334.jpg"},{"id":"702344","title":"Gasthof Andreas","price":446,"currency":"EUR","country":"Oostenrijk","departure":"","departureDate":"2026-05-27","duration":4,"stars":"3","province":"","region":"Tirol","serviceType":"HP","url":"https://reis.tui.nl/c?c=433&m=1564650&a=453979&r=hackerdeal2.0&u=https%3A%2F%2Fwww.tui.nl%2Fgasthof-andreas-509702344%2F%3FDepartureDate%3D2026-05-27%26Duration%3D4%26TransportType%3D2","banner":"https://media.tuicontent.nl/91B/91B245FBFA2F89C675C87C9DC4252755.jpg"},{"id":"1014845","title":"Victoriya","price":448,"currency":"EUR","country":"Oostenrijk","departure":"","departureDate":"2026-10-01","duration":4,"stars":"3","province":"","region":"Kitzsteinhorn Maiskogel","serviceType":"AI","url":"https://reis.tui.nl/c?c=433&m=1564650&a=453979&r=hackerdeal2.0&u=https%3A%2F%2Fwww.tui.nl%2Fvictoriya-5091014845%2F%3FDepartureDate%3D2026-10-01%26Duration%3D4%26TransportType%3D2","banner":"https://media.tuicontent.nl/BB1/BB14D8575631F5BCD2627D57524D0E3B.jpg"},{"id":"165682","title":"Montanara","price":452,"currency":"EUR","country":"Oostenrijk","departure":"","departureDate":"2026-07-02","duration":4,"stars":"4","province":"","region":"Salzburger Sportwelt","serviceType":"LO","url":"https://reis.tui.nl/c?c=433&m=1564650&a=453979&r=hackerdeal2.0&u=https%3A%2F%2Fwww.tui.nl%2Fmontanara-509165682%2F%3FDepartureDate%3D2026-07-02%26Duration%3D4%26TransportType%3D2","banner":"https://media.tuicontent.nl/AAC/AAC798F0A07589B0871916D53FA171AC.jpg"},{"id":"991141","title":"Campanile Vienna South","price":467,"currency":"EUR","country":"Oostenrijk","departure":"","departureDate":"2026-07-01","duration":4,"stars":"3","province":"","region":"Wenen","serviceType":"LG","url":"https://reis.tui.nl/c?c=433&m=1564650&a=453979&r=hackerdeal2.0&u=https%3A%2F%2Fwww.tui.nl%2Fcampanile-vienna-south-509991141%2F%3FDepartureDate%3D2026-07-01%26Duration%3D4%26TransportType%3D2","banner":"https://media.tuicontent.nl/0A7/0A7D27F0843628B5D1F0C9D2EC8BE3E9.jpg"},{"id":"671704","title":"Ibis Wien City","price":473,"currency":"EUR","country":"Oostenrijk","departure":"","departureDate":"2026-07-01","duration":4,"stars":"3","province":"","region":"Wenen","serviceType":"LO","url":"https://reis.tui.nl/c?c=433&m=1564650&a=453979&r=hackerdeal2.0&u=https%3A%2F%2Fwww.tui.nl%2Fibis-wien-city-509671704%2F%3FDepartureDate%3D2026-07-01%26Duration%3D4%26TransportType%3D2","banner":"https://media.tuicontent.nl/EDD/EDDA6EF221909413F32BA5A0D79E906D.jpg"},{"id":"620579","title":"Ibis Wien Mariahilf","price":475,"currency":"EUR","country":"Oostenrijk","departure":"","departureDate":"2026-07-01","duration":4,"stars":"3","province":"","region":"Wenen","serviceType":"LG","url":"https://reis.tui.nl/c?c=433&m=1564650&a=453979&r=hackerdeal2.0&u=https%3A%2F%2Fwww.tui.nl%2Fibis-wien-mariahilf-509620579%2F%3FDepartureDate%3D2026-07-01%26Duration%3D4%26TransportType%3D2","banner":"https://media.tuicontent.nl/09F/09F65CFED39D50D5C6742B89BD08A4CE.jpg"},{"id":"77428","title":"Centerhouse Wagrainerhof","price":477,"currency":"EUR","country":"Oostenrijk","departure":"","departureDate":"2026-06-11","duration":4,"stars":"4","province":"","region":"Salzburger Sportwelt","serviceType":"LG","url":"https://reis.tui.nl/c?c=433&m=1564650&a=453979&r=hackerdeal2.0&u=https%3A%2F%2Fwww.tui.nl%2Fcenterhouse-wagrainerhof-50977428%2F%3FDepartureDate%3D2026-06-11%26Duration%3D4%26TransportType%3D2","banner":"https://media.tuicontent.nl/FD8/FD8A102B5D3DFD49A391CED038FA1ECD.jpg"},{"id":"78997","title":"Basur","price":479,"currency":"EUR","country":"Oostenrijk","departure":"","departureDate":"2026-08-30","duration":4,"stars":"3","province":"","region":"Ski Arlberg","serviceType":"HP","url":"https://reis.tui.nl/c?c=433&m=1564650&a=453979&r=hackerdeal2.0&u=https%3A%2F%2Fwww.tui.nl%2Fbasur-50978997%2F%3FDepartureDate%3D2026-08-30%26Duration%3D4%26TransportType%3D2","banner":"https://media.tuicontent.nl/1B6/1B6CC955C1A8E0E5A5F8B0051D36335D.jpg"},{"id":"698774","title":"Jäger","price":480,"currency":"EUR","country":"Oostenrijk","departure":"","departureDate":"2026-09-27","duration":4,"stars":"3","province":"","region":"Tirol","serviceType":"HP","url":"https://reis.tui.nl/c?c=433&m=1564650&a=453979&r=hackerdeal2.0&u=https%3A%2F%2Fwww.tui.nl%2Fjager-509698774%2F%3FDepartureDate%3D2026-09-27%26Duration%3D4%26TransportType%3D2","banner":"https://media.tuicontent.nl/7FE/7FE2D4F0450C65B7FE292D9AF2DCAA69.jpg"},{"id":"1003658","title":"NH Vienna Airport Conference Center","price":481,"currency":"EUR","country":"Oostenrijk","departure":"","departureDate":"2026-08-26","duration":4,"stars":"4","province":"","region":"Wenen","serviceType":"LG","url":"https://reis.tui.nl/c?c=433&m=1564650&a=453979&r=hackerdeal2.0&u=https%3A%2F%2Fwww.tui.nl%2Fnh-vienna-airport-conference-center-5091003658%2F%3FDepartureDate%3D2026-08-26%26Duration%3D4%26TransportType%3D2","banner":"https://media.tuicontent.nl/914/9143632B53878756BE626CCFFB1E1A44.jpg"},{"id":"974517","title":"Victoria","price":484,"currency":"EUR","country":"Oostenrijk","departure":"","departureDate":"2026-10-01","duration":4,"stars":"4","province":"","region":"Saalbach Hinterglemm Leogang Fieberbrunn","serviceType":"HP","url":"https://reis.tui.nl/c?c=433&m=1564650&a=453979&r=hackerdeal2.0&u=https%3A%2F%2Fwww.tui.nl%2Fvictoria-509974517%2F%3FDepartureDate%3D2026-10-01%26Duration%3D4%26TransportType%3D2","banner":"https://media.tuicontent.nl/B7A/B7A08B861BC307355DF69BDD7F3D6481.jpg"},{"id":"962313","title":"Calmo","price":487,"currency":"EUR","country":"Oostenrijk","departure":"","departureDate":"2026-07-01","duration":4,"stars":"3","province":"","region":"Wenen","serviceType":"LG","url":"https://reis.tui.nl/c?c=433&m=1564650&a=453979&r=hackerdeal2.0&u=https%3A%2F%2Fwww.tui.nl%2Fcalmo-509962313%2F%3FDepartureDate%3D2026-07-01%26Duration%3D4%26TransportType%3D2","banner":"https://media.tuicontent.nl/56E/56EAE07E80D0E6A74FB21CD3C88802D8.jpg"},{"id":"59044","title":"Schlosshotel Rosenegg","price":494,"currency":"EUR","country":"Oostenrijk","departure":"","departureDate":"2026-07-02","duration":4,"stars":"4","province":"","region":"Kitzbüheler Alpen","serviceType":"LG","url":"https://reis.tui.nl/c?c=433&m=1564650&a=453979&r=hackerdeal2.0&u=https%3A%2F%2Fwww.tui.nl%2Fschlosshotel-rosenegg-50959044%2F%3FDepartureDate%3D2026-07-02%26Duration%3D4%26TransportType%3D2","banner":"https://media.tuicontent.nl/E79/E795D333EBFB7AE0C604E598FA83AF79.jpg"},{"id":"172484","title":"Kertess","price":498,"currency":"EUR","country":"Oostenrijk","departure":"","departureDate":"2026-06-14","duration":4,"stars":"4","province":"","region":"Ski Arlberg","serviceType":"HP","url":"https://reis.tui.nl/c?c=433&m=1564650&a=453979&r=hackerdeal2.0&u=https%3A%2F%2Fwww.tui.nl%2Fkertess-509172484%2F%3FDepartureDate%3D2026-06-14%26Duration%3D4%26TransportType%3D2","banner":"https://media.tuicontent.nl/482/4826D4E2CA69DE05D36A2B44915F6550.jpg"},{"id":"42797","title":"Tirolerhof","price":501,"currency":"EUR","country":"Oostenrijk","departure":"","departureDate":"2026-09-20","duration":4,"stars":"4","province":"","region":"Oberinntal","serviceType":"LO","url":"https://reis.tui.nl/c?c=433&m=1564650&a=453979&r=hackerdeal2.0&u=https%3A%2F%2Fwww.tui.nl%2Ftirolerhof-50942797%2F%3FDepartureDate%3D2026-09-20%26Duration%3D4%26TransportType%3D2","banner":"https://media.tuicontent.nl/CBD/CBD6BED26649B9E1CD28033001DD1F99.jpg"},{"id":"414766","title":"Clarion Hotel Vienna South","price":506,"currency":"EUR","country":"Oostenrijk","departure":"","departureDate":"2026-06-12","duration":4,"stars":"4","province":"","region":"Wenen","serviceType":"LO","url":"https://reis.tui.nl/c?c=433&m=1564650&a=453979&r=hackerdeal2.0&u=https%3A%2F%2Fwww.tui.nl%2Fclarion-hotel-vienna-south-509414766%2F%3FDepartureDate%3D2026-06-12%26Duration%3D4%26TransportType%3D2","banner":"https://media.tuicontent.nl/B71/B71774906CDDF9EFFD7FB3B19F9E6DFA.jpg"},{"id":"541982","title":"Alpenhotel Edelweiss","price":506,"currency":"EUR","country":"Oostenrijk","departure":"","departureDate":"2026-09-27","duration":4,"stars":"3","province":"","region":"Achensee","serviceType":"HP","url":"https://reis.tui.nl/c?c=433&m=1564650&a=453979&r=hackerdeal2.0&u=https%3A%2F%2Fwww.tui.nl%2Falpenhotel-edelweiss-509541982%2F%3FDepartureDate%3D2026-09-27%26Duration%3D4%26TransportType%3D2","banner":"https://media.tuicontent.nl/930/9307F4971CC671670B2F22876F8E1998.jpg"},{"id":"1017219","title":"Exe Vienna","price":508,"currency":"EUR","country":"Oostenrijk","departure":"","departureDate":"2026-07-01","duration":4,"stars":"4","province":"","region":"Wenen","serviceType":"LO","url":"https://reis.tui.nl/c?c=433&m=1564650&a=453979&r=hackerdeal2.0&u=https%3A%2F%2Fwww.tui.nl%2Fexe-vienna-5091017219%2F%3FDepartureDate%3D2026-07-01%26Duration%3D4%26TransportType%3D2","banner":"https://media.tuicontent.nl/8B7/8B7740AFA43E8EEAA96F0DEEA3BA3865.jpg"},{"id":"991139","title":"B&B Wien Meidling","price":508,"currency":"EUR","country":"Oostenrijk","departure":"","departureDate":"2026-07-01","duration":4,"stars":"3","province":"","region":"Wenen","serviceType":"LG","url":"https://reis.tui.nl/c?c=433&m=1564650&a=453979&r=hackerdeal2.0&u=https%3A%2F%2Fwww.tui.nl%2Fbenb-wien-meidling-509991139%2F%3FDepartureDate%3D2026-07-01%26Duration%3D4%26TransportType%3D2","banner":"https://media.tuicontent.nl/C89/C893B947E1F9A352F00D649A32068A82.jpg"},{"id":"988434","title":"Heart Hotel Nordstern","price":511,"currency":"EUR","country":"Oostenrijk","departure":"","departureDate":"2026-06-28","duration":4,"stars":"","province":"","region":"Tirol","serviceType":"HP","url":"https://reis.tui.nl/c?c=433&m=1564650&a=453979&r=hackerdeal2.0&u=https%3A%2F%2Fwww.tui.nl%2Fheart-hotel-nordstern-509988434%2F%3FDepartureDate%3D2026-06-28%26Duration%3D4%26TransportType%3D2","banner":"https://media.tuicontent.nl/6CD/6CDCEDC08E1D4357CD52DE28BAF98503.jpg"},{"id":"653246","title":"Roomz Vienna Prater","price":513,"currency":"EUR","country":"Oostenrijk","departure":"","departureDate":"2026-05-16","duration":4,"stars":"4","province":"","region":"Wenen","serviceType":"-","url":"https://reis.tui.nl/c?c=433&m=1564650&a=453979&r=hackerdeal2.0&u=https%3A%2F%2Fwww.tui.nl%2Froomz-vienna-prater-509653246%2F%3FDepartureDate%3D2026-05-16%26Duration%3D4%26TransportType%3D2","banner":"https://media.tuicontent.nl/4B7/4B718B17776683C0445B9068D30D94B8.jpg"},{"id":"22552","title":"Bellevue","price":514,"currency":"EUR","country":"Oostenrijk","departure":"","departureDate":"2026-07-01","duration":4,"stars":"4","province":"","region":"Wenen","serviceType":"LG","url":"https://reis.tui.nl/c?c=433&m=1564650&a=453979&r=hackerdeal2.0&u=https%3A%2F%2Fwww.tui.nl%2Fbellevue-50922552%2F%3FDepartureDate%3D2026-07-01%26Duration%3D4%26TransportType%3D2","banner":"https://media.tuicontent.nl/DBA/DBAEBF00F2330B0593142ED67E6275EA.jpg"},{"id":"548714","title":"Apart Fliana Mathon","price":518,"currency":"EUR","country":"Oostenrijk","departure":"","departureDate":"2026-09-05","duration":5,"stars":"3","province":"","region":"Paznauntal","serviceType":"LG","url":"https://reis.tui.nl/c?c=433&m=1564650&a=453979&r=hackerdeal2.0&u=https%3A%2F%2Fwww.tui.nl%2Fapart-fliana-mathon-509548714%2F%3FDepartureDate%3D2026-09-05%26Duration%3D5%26TransportType%3D2","banner":"https://media.tuicontent.nl/13C/13C89705087DD1AC076E59827BD2647A.jpg"},{"id":"1003865","title":"Alt Vent Tyrol","price":519,"currency":"EUR","country":"Oostenrijk","departure":"","departureDate":"2026-06-28","duration":4,"stars":"3","province":"","region":"Ötztal","serviceType":"LO","url":"https://reis.tui.nl/c?c=433&m=1564650&a=453979&r=hackerdeal2.0&u=https%3A%2F%2Fwww.tui.nl%2Falt-vent-tyrol-5091003865%2F%3FDepartureDate%3D2026-06-28%26Duration%3D4%26TransportType%3D2","banner":"https://media.tuicontent.nl/5E2/5E200CBBDDBE4CBF9A786F176FFB91D3.jpg"},{"id":"522306","title":"Vent","price":519,"currency":"EUR","country":"Oostenrijk","departure":"","departureDate":"2026-06-28","duration":4,"stars":"4","province":"","region":"Ötztal","serviceType":"LO","url":"https://reis.tui.nl/c?c=433&m=1564650&a=453979&r=hackerdeal2.0&u=https%3A%2F%2Fwww.tui.nl%2Fvent-509522306%2F%3FDepartureDate%3D2026-06-28%26Duration%3D4%26TransportType%3D2","banner":"https://media.tuicontent.nl/7CE/7CE607C45700BFE00756C00B01968C11.jpg"},{"id":"51035","title":"Strudlhof","price":520,"currency":"EUR","country":"Oostenrijk","departure":"","departureDate":"2026-06-26","duration":4,"stars":"4","province":"","region":"Wenen","serviceType":"LO","url":"https://reis.tui.nl/c?c=433&m=1564650&a=453979&r=hackerdeal2.0&u=https%3A%2F%2Fwww.tui.nl%2Fstrudlhof-50951035%2F%3FDepartureDate%3D2026-06-26%26Duration%3D4%26TransportType%3D2","banner":"https://media.tuicontent.nl/92B/92BD6A22D62A3A6DEE90077C546439D4.jpg"},{"id":"50393","title":"Klingler","price":520,"currency":"EUR","country":"Oostenrijk","departure":"","departureDate":"2027-01-03","duration":4,"stars":"3","province":"","region":"Achensee","serviceType":"LO","url":"https://reis.tui.nl/c?c=433&m=1564650&a=453979&r=hackerdeal2.0&u=https%3A%2F%2Fwww.tui.nl%2Fklingler-50950393%2F%3FDepartureDate%3D2027-01-03%26Duration%3D4%26TransportType%3D2","banner":"https://media.tuicontent.nl/952/9521DC2B21A99F0122080C7EDA1BFB9D.jpg"},{"id":"577695","title":"Zeitgeist Vienna","price":522,"currency":"EUR","country":"Oostenrijk","departure":"","departureDate":"2026-06-12","duration":4,"stars":"4","province":"","region":"Wenen","serviceType":"LO","url":"https://reis.tui.nl/c?c=433&m=1564650&a=453979&r=hackerdeal2.0&u=https%3A%2F%2Fwww.tui.nl%2Fzeitgeist-vienna-509577695%2F%3FDepartureDate%3D2026-06-12%26Duration%3D4%26TransportType%3D2","banner":"https://media.tuicontent.nl/91A/91AAFF465A1F28BF43C0A94B5E44B3ED.jpg"},{"id":"70319","title":"Sonnschein","price":523,"currency":"EUR","country":"Oostenrijk","departure":"","departureDate":"2026-09-27","duration":4,"stars":"4","province":"","region":"Ski Juwel Alpbachtal Wildschönau","serviceType":"HP","url":"https://reis.tui.nl/c?c=433&m=1564650&a=453979&r=hackerdeal2.0&u=https%3A%2F%2Fwww.tui.nl%2Fsonnschein-50970319%2F%3FDepartureDate%3D2026-09-27%26Duration%3D4%26TransportType%3D2","banner":"https://media.tuicontent.nl/CD4/CD429E549B4D26209BBECB1625327170.jpg"},{"id":"529471","title":"Innertalerhof","price":525,"currency":"EUR","country":"Oostenrijk","departure":"","departureDate":"2026-09-27","duration":4,"stars":"4","province":"","region":"Tirol","serviceType":"HP","url":"https://reis.tui.nl/c?c=433&m=1564650&a=453979&r=hackerdeal2.0&u=https%3A%2F%2Fwww.tui.nl%2Finnertalerhof-509529471%2F%3FDepartureDate%3D2026-09-27%26Duration%3D4%26TransportType%3D2","banner":"https://media.tuicontent.nl/9EE/9EEA85F2CA8B2B3DC0DA1E9E93E5C866.jpg"},{"id":"603914","title":"TUI BLUE Schladming","price":528,"currency":"EUR","country":"Oostenrijk","departure":"","departureDate":"2026-10-01","duration":4,"stars":"3","province":"","region":"Dachstein Tauern","serviceType":"HP","url":"https://reis.tui.nl/c?c=433&m=1564650&a=453979&r=hackerdeal2.0&u=https%3A%2F%2Fwww.tui.nl%2Ftui-blue-schladming-509603914%2F%3FDepartureDate%3D2026-10-01%26Duration%3D4%26TransportType%3D2","banner":"https://media.tuicontent.nl/699/699BB506377855C5E2302D155E8493C5.jpg"},{"id":"202678","title":"Boutiquehotel Stadthalle","price":531,"currency":"EUR","country":"Oostenrijk","departure":"","departureDate":"2026-07-01","duration":4,"stars":"3","province":"","region":"Wenen","serviceType":"LG","url":"https://reis.tui.nl/c?c=433&m=1564650&a=453979&r=hackerdeal2.0&u=https%3A%2F%2Fwww.tui.nl%2Fboutiquehotel-stadthalle-509202678%2F%3FDepartureDate%3D2026-07-01%26Duration%3D4%26TransportType%3D2","banner":"https://media.tuicontent.nl/4D9/4D9D31B50F29BF7F1B566E76A24936D0.jpg"},{"id":"961913","title":"The Weekend","price":534,"currency":"EUR","country":"Oostenrijk","departure":"","departureDate":"2026-07-01","duration":4,"stars":"4","province":"","region":"Wenen","serviceType":"LG","url":"https://reis.tui.nl/c?c=433&m=1564650&a=453979&r=hackerdeal2.0&u=https%3A%2F%2Fwww.tui.nl%2Fthe-weekend-509961913%2F%3FDepartureDate%3D2026-07-01%26Duration%3D4%26TransportType%3D2","banner":"https://media.tuicontent.nl/414/414E2F2A313516B239EEF3F7D9648993.jpg"},{"id":"699568","title":"Harry&apos;s Home Wien","price":535,"currency":"EUR","country":"Oostenrijk","departure":"","departureDate":"2026-06-10","duration":4,"stars":"4","province":"","region":"Wenen","serviceType":"LO","url":"https://reis.tui.nl/c?c=433&m=1564650&a=453979&r=hackerdeal2.0&u=https%3A%2F%2Fwww.tui.nl%2Fharry-s-home-wien-509699568%2F%3FDepartureDate%3D2026-06-10%26Duration%3D4%26TransportType%3D2","banner":"https://media.tuicontent.nl/BC3/BC387E2EC0D7D64B8C8859055A381892.jpg"},{"id":"961912","title":"Leonardo Vienna City West","price":543,"currency":"EUR","country":"Oostenrijk","departure":"","departureDate":"2026-07-01","duration":4,"stars":"3","province":"","region":"Wenen","serviceType":"LG","url":"https://reis.tui.nl/c?c=433&m=1564650&a=453979&r=hackerdeal2.0&u=https%3A%2F%2Fwww.tui.nl%2Fleonardo-vienna-city-west-509961912%2F%3FDepartureDate%3D2026-07-01%26Duration%3D4%26TransportType%3D2","banner":"https://media.tuicontent.nl/F28/F284F575F942E84CA5C46A1347A7423D.jpg"},{"id":"987175","title":"Heart Hotel Arlberg","price":544,"currency":"EUR","country":"Oostenrijk","departure":"","departureDate":"2026-06-28","duration":4,"stars":"","province":"","region":"Ski Arlberg","serviceType":"HP","url":"https://reis.tui.nl/c?c=433&m=1564650&a=453979&r=hackerdeal2.0&u=https%3A%2F%2Fwww.tui.nl%2Fheart-hotel-arlberg-509987175%2F%3FDepartureDate%3D2026-06-28%26Duration%3D4%26TransportType%3D2","banner":"https://media.tuicontent.nl/ACC/ACCD052C4296226D7A6445F8A03E5948.jpg"},{"id":"961911","title":"Ibis Styles Wien Messe Prater","price":548,"currency":"EUR","country":"Oostenrijk","departure":"","departureDate":"2026-07-01","duration":4,"stars":"3","province":"","region":"Wenen","serviceType":"LG","url":"https://reis.tui.nl/c?c=433&m=1564650&a=453979&r=hackerdeal2.0&u=https%3A%2F%2Fwww.tui.nl%2Fibis-styles-wien-messe-prater-509961911%2F%3FDepartureDate%3D2026-07-01%26Duration%3D4%26TransportType%3D2","banner":"https://media.tuicontent.nl/9B7/9B7A821A3895EEFFDDB3357A3C160FC8.jpg"},{"id":"962314","title":"Ruby Marie","price":552,"currency":"EUR","country":"Oostenrijk","departure":"","departureDate":"2026-07-01","duration":4,"stars":"4","province":"","region":"Wenen","serviceType":"-","url":"https://reis.tui.nl/c?c=433&m=1564650&a=453979&r=hackerdeal2.0&u=https%3A%2F%2Fwww.tui.nl%2Fruby-marie-509962314%2F%3FDepartureDate%3D2026-07-01%26Duration%3D4%26TransportType%3D2","banner":"https://media.tuicontent.nl/00F/00FA7D297E4B2F507124D7E307E93137.jpg"},{"id":"57506","title":"Schörhof","price":564,"currency":"EUR","country":"Oostenrijk","departure":"","departureDate":"2026-07-02","duration":4,"stars":"4","province":"","region":"Hochkönig","serviceType":"HP","url":"https://reis.tui.nl/c?c=433&m=1564650&a=453979&r=hackerdeal2.0&u=https%3A%2F%2Fwww.tui.nl%2Fschorhof-50957506%2F%3FDepartureDate%3D2026-07-02%26Duration%3D4%26TransportType%3D2","banner":"https://media.tuicontent.nl/B59/B596BF9EB4B522353FED1320450923F2.jpg"},{"id":"535952","title":"NH Wien City","price":566,"currency":"EUR","country":"Oostenrijk","departure":"","departureDate":"2026-07-01","duration":4,"stars":"4","province":"","region":"Wenen","serviceType":"LG","url":"https://reis.tui.nl/c?c=433&m=1564650&a=453979&r=hackerdeal2.0&u=https%3A%2F%2Fwww.tui.nl%2Fnh-wien-city-509535952%2F%3FDepartureDate%3D2026-07-01%26Duration%3D4%26TransportType%3D2","banner":"https://media.tuicontent.nl/B9D/B9D5152C88AF639F1547EFD50C21B4FE.jpg"},{"id":"628827","title":"Lindner am Belvedere","price":569,"currency":"EUR","country":"Oostenrijk","departure":"","departureDate":"2026-07-01","duration":4,"stars":"4","province":"","region":"Wenen","serviceType":"LG","url":"https://reis.tui.nl/c?c=433&m=1564650&a=453979&r=hackerdeal2.0&u=https%3A%2F%2Fwww.tui.nl%2Flindner-am-belvedere-509628827%2F%3FDepartureDate%3D2026-07-01%26Duration%3D4%26TransportType%3D2","banner":"https://media.tuicontent.nl/8F5/8F55574A5CF3B90589F7721103DFFDFB.jpg"},{"id":"690903","title":"Lohmann","price":570,"currency":"EUR","country":"Oostenrijk","departure":"","departureDate":"2026-08-30","duration":4,"stars":"3","province":"","region":"Obergurgl Hochgurgl","serviceType":"HP","url":"https://reis.tui.nl/c?c=433&m=1564650&a=453979&r=hackerdeal2.0&u=https%3A%2F%2Fwww.tui.nl%2Flohmann-509690903%2F%3FDepartureDate%3D2026-08-30%26Duration%3D4%26TransportType%3D2","banner":"https://media.tuicontent.nl/297/297F84264F93738D399C967A7EC6157E.jpg"},{"id":"962311","title":"B&B Wien Hauptbahnhof","price":572,"currency":"EUR","country":"Oostenrijk","departure":"","departureDate":"2026-07-01","duration":4,"stars":"2","province":"","region":"Wenen","serviceType":"LG","url":"https://reis.tui.nl/c?c=433&m=1564650&a=453979&r=hackerdeal2.0&u=https%3A%2F%2Fwww.tui.nl%2Fbenb-wien-hauptbahnhof-509962311%2F%3FDepartureDate%3D2026-07-01%26Duration%3D4%26TransportType%3D2","banner":"https://media.tuicontent.nl/1AC/1AC4D65748B593309FF55B307B7E9026.jpg"},{"id":"520680","title":"Wiesenrand","price":574,"currency":"EUR","country":"Oostenrijk","departure":"","departureDate":"2026-09-19","duration":5,"stars":"3","province":"","region":"Ötztal","serviceType":"LG","url":"https://reis.tui.nl/c?c=433&m=1564650&a=453979&r=hackerdeal2.0&u=https%3A%2F%2Fwww.tui.nl%2Fwiesenrand-509520680%2F%3FDepartureDate%3D2026-09-19%26Duration%3D5%26TransportType%3D2","banner":"https://media.tuicontent.nl/7B7/7B7C422D8E94591FDB52649228104022.jpg"},{"id":"559816","title":"Alpenparks Central","price":578,"currency":"EUR","country":"Oostenrijk","departure":"","departureDate":"2026-10-22","duration":4,"stars":"4","province":"","region":"Salzburgerland","serviceType":"LG","url":"https://reis.tui.nl/c?c=433&m=1564650&a=453979&r=hackerdeal2.0&u=https%3A%2F%2Fwww.tui.nl%2Falpenparks-central-509559816%2F%3FDepartureDate%3D2026-10-22%26Duration%3D4%26TransportType%3D2","banner":"https://media.tuicontent.nl/562/562AE3B4F2791225BD40D1DBE2E66074.jpg"},{"id":"11543","title":"Regina","price":580,"currency":"EUR","country":"Oostenrijk","departure":"","departureDate":"2027-01-10","duration":5,"stars":"4","province":"","region":"Oberinntal","serviceType":"HP","url":"https://reis.tui.nl/c?c=433&m=1564650&a=453979&r=hackerdeal2.0&u=https%3A%2F%2Fwww.tui.nl%2Fregina-50911543%2F%3FDepartureDate%3D2027-01-10%26Duration%3D5%26TransportType%3D2","banner":"https://media.tuicontent.nl/6B7/6B76B208032E010F7118883B4BE4CA26.jpg"},{"id":"778318","title":"Evergrün KAPRUN","price":600,"currency":"EUR","country":"Oostenrijk","departure":"","departureDate":"2026-10-01","duration":4,"stars":"4","province":"","region":"Kitzsteinhorn Maiskogel","serviceType":"HP","url":"https://reis.tui.nl/c?c=433&m=1564650&a=453979&r=hackerdeal2.0&u=https%3A%2F%2Fwww.tui.nl%2Fevergrun-kaprun-509778318%2F%3FDepartureDate%3D2026-10-01%26Duration%3D4%26TransportType%3D2","banner":"https://media.tuicontent.nl/68D/68DEA4A3640FBAAB866C60473B3AB5EC.jpg"},{"id":"1003657","title":"NH Collection Wien Zentrum","price":602,"currency":"EUR","country":"Oostenrijk","departure":"","departureDate":"2026-07-01","duration":4,"stars":"4","province":"","region":"Wenen","serviceType":"LG","url":"https://reis.tui.nl/c?c=433&m=1564650&a=453979&r=hackerdeal2.0&u=https%3A%2F%2Fwww.tui.nl%2Fnh-collection-wien-zentrum-5091003657%2F%3FDepartureDate%3D2026-07-01%26Duration%3D4%26TransportType%3D2","banner":"https://media.tuicontent.nl/93F/93F75011F102B4EE9AD299D5A10D125F.jpg"},{"id":"574095","title":"Daniel","price":605,"currency":"EUR","country":"Oostenrijk","departure":"","departureDate":"2026-07-01","duration":4,"stars":"4","province":"","region":"Wenen","serviceType":"LG","url":"https://reis.tui.nl/c?c=433&m=1564650&a=453979&r=hackerdeal2.0&u=https%3A%2F%2Fwww.tui.nl%2Fdaniel-509574095%2F%3FDepartureDate%3D2026-07-01%26Duration%3D4%26TransportType%3D2","banner":"https://media.tuicontent.nl/7F3/7F31DBB01CD9F2ED64CDC3BFD9A6A9E3.jpg"},{"id":"65986","title":"Crystal","price":606,"currency":"EUR","country":"Oostenrijk","departure":"","departureDate":"2027-01-03","duration":4,"stars":"4","province":"","region":"Hochzillertal Hochfügen","serviceType":"HP","url":"https://reis.tui.nl/c?c=433&m=1564650&a=453979&r=hackerdeal2.0&u=https%3A%2F%2Fwww.tui.nl%2Fcrystal-50965986%2F%3FDepartureDate%3D2027-01-03%26Duration%3D4%26TransportType%3D2","banner":"https://media.tuicontent.nl/97C/97C4959D88A716332985F22CEE1754E2.jpg"},{"id":"693868","title":"Rauriserhof","price":614,"currency":"EUR","country":"Oostenrijk","departure":"","departureDate":"2026-10-01","duration":4,"stars":"4","province":"","region":"Rauriser Hochalmbahnen","serviceType":"VP","url":"https://reis.tui.nl/c?c=433&m=1564650&a=453979&r=hackerdeal2.0&u=https%3A%2F%2Fwww.tui.nl%2Frauriserhof-509693868%2F%3FDepartureDate%3D2026-10-01%26Duration%3D4%26TransportType%3D2","banner":"https://media.tuicontent.nl/802/80217D4ABF3BC1B55EE9D2B1725109EB.jpg"},{"id":"714502","title":"25hours Vienna MuseumsQuartier","price":622,"currency":"EUR","country":"Oostenrijk","departure":"","departureDate":"2026-07-01","duration":4,"stars":"4","province":"","region":"Wenen","serviceType":"LO","url":"https://reis.tui.nl/c?c=433&m=1564650&a=453979&r=hackerdeal2.0&u=https%3A%2F%2Fwww.tui.nl%2F25hours-vienna-museumsquartier-509714502%2F%3FDepartureDate%3D2026-07-01%26Duration%3D4%26TransportType%3D2","banner":"https://media.tuicontent.nl/0A4/0A4A1A8095F88AFD9ED927EDCADD7E42.jpg"},{"id":"12383","title":"Alpina Deluxe","price":630,"currency":"EUR","country":"Oostenrijk","departure":"","departureDate":"2026-06-28","duration":4,"stars":"4","province":"","region":"Obergurgl Hochgurgl","serviceType":"HP","url":"https://reis.tui.nl/c?c=433&m=1564650&a=453979&r=hackerdeal2.0&u=https%3A%2F%2Fwww.tui.nl%2Falpina-deluxe-50912383%2F%3FDepartureDate%3D2026-06-28%26Duration%3D4%26TransportType%3D2","banner":"https://media.tuicontent.nl/A3C/A3C16513EC042810493D3BB9C58061BF.jpg"},{"id":"40518","title":"Austria Classic Wien","price":631,"currency":"EUR","country":"Oostenrijk","departure":"","departureDate":"2026-07-01","duration":4,"stars":"3","province":"","region":"Wenen","serviceType":"LG","url":"https://reis.tui.nl/c?c=433&m=1564650&a=453979&r=hackerdeal2.0&u=https%3A%2F%2Fwww.tui.nl%2Faustria-classic-wien-50940518%2F%3FDepartureDate%3D2026-07-01%26Duration%3D4%26TransportType%3D2","banner":"https://media.tuicontent.nl/E95/E955D95808FD557A179DE5AA9606B816.jpg"},{"id":"693869","title":"Urslauerhof","price":644,"currency":"EUR","country":"Oostenrijk","departure":"","departureDate":"2026-10-01","duration":4,"stars":"4","province":"","region":"Hochkönig","serviceType":"LO","url":"https://reis.tui.nl/c?c=433&m=1564650&a=453979&r=hackerdeal2.0&u=https%3A%2F%2Fwww.tui.nl%2Furslauerhof-509693869%2F%3FDepartureDate%3D2026-10-01%26Duration%3D4%26TransportType%3D2","banner":"https://media.tuicontent.nl/893/893DCD61460D92B42572B8FB2D0A20B9.jpg"},{"id":"691934","title":"Parkhotel Kirchberg","price":645,"currency":"EUR","country":"Oostenrijk","departure":"","departureDate":"2027-03-16","duration":4,"stars":"3","province":"","region":"Kitzbühel Kirchberg","serviceType":"LO","url":"https://reis.tui.nl/c?c=433&m=1564650&a=453979&r=hackerdeal2.0&u=https%3A%2F%2Fwww.tui.nl%2Fparkhotel-kirchberg-509691934%2F%3FDepartureDate%3D2027-03-16%26Duration%3D4%26TransportType%3D2","banner":"https://media.tuicontent.nl/AE2/AE2E8BE7BD99104CC8ADBFB1DAE65612.jpg"},{"id":"60984","title":"Harfenwirt","price":650,"currency":"EUR","country":"Oostenrijk","departure":"","departureDate":"2027-03-23","duration":4,"stars":"3","province":"","region":"Ski Juwel Alpbachtal Wildschönau","serviceType":"HP","url":"https://reis.tui.nl/c?c=433&m=1564650&a=453979&r=hackerdeal2.0&u=https%3A%2F%2Fwww.tui.nl%2Fharfenwirt-50960984%2F%3FDepartureDate%3D2027-03-23%26Duration%3D4%26TransportType%3D2","banner":"https://media.tuicontent.nl/12E/12E25A6FC6AC54BA8C01918DFA514A72.jpg"},{"id":"973154","title":"Appartementen Alpenstyle Fieberbrunn","price":651,"currency":"EUR","country":"Oostenrijk","departure":"","departureDate":"2026-10-01","duration":4,"stars":"4","province":"","region":"Kitzbüheler Alpen","serviceType":"LG","url":"https://reis.tui.nl/c?c=433&m=1564650&a=453979&r=hackerdeal2.0&u=https%3A%2F%2Fwww.tui.nl%2Fappartementen-alpenstyle-fieberbrunn-509973154%2F%3FDepartureDate%3D2026-10-01%26Duration%3D4%26TransportType%3D2","banner":"https://media.tuicontent.nl/9B0/9B05BB7C215A6EFF3536B73A7F038505.jpg"},{"id":"743282","title":"Zoku Vienna","price":656,"currency":"EUR","country":"Oostenrijk","departure":"","departureDate":"2026-07-01","duration":4,"stars":"4","province":"","region":"Wenen","serviceType":"LG","url":"https://reis.tui.nl/c?c=433&m=1564650&a=453979&r=hackerdeal2.0&u=https%3A%2F%2Fwww.tui.nl%2Fzoku-vienna-509743282%2F%3FDepartureDate%3D2026-07-01%26Duration%3D4%26TransportType%3D2","banner":"https://media.tuicontent.nl/3EC/3ECDE7DEA25C419FCD6AFB1A93B9962A.jpg"},{"id":"508971","title":"Hochland","price":660,"currency":"EUR","country":"Oostenrijk","departure":"","departureDate":"2026-07-01","duration":6,"stars":"4","province":"","region":"Oberinntal","serviceType":"LG","url":"https://reis.tui.nl/c?c=433&m=1564650&a=453979&r=hackerdeal2.0&u=https%3A%2F%2Fwww.tui.nl%2Fhochland-509508971%2F%3FDepartureDate%3D2026-07-01%26Duration%3D6%26TransportType%3D2","banner":"https://media.tuicontent.nl/031/031A5F254F0E53F49CA838F3F00A78C2.jpg"},{"id":"16289","title":"Mercure Grand Hotel Biedermeier","price":673,"currency":"EUR","country":"Oostenrijk","departure":"","departureDate":"2026-07-01","duration":4,"stars":"4","province":"","region":"Wenen","serviceType":"LO","url":"https://reis.tui.nl/c?c=433&m=1564650&a=453979&r=hackerdeal2.0&u=https%3A%2F%2Fwww.tui.nl%2Fmercure-grand-hotel-biedermeier-50916289%2F%3FDepartureDate%3D2026-07-01%26Duration%3D4%26TransportType%3D2","banner":"https://media.tuicontent.nl/96E/96EF0E7489EF9D567B45433221C2B262.jpg"},{"id":"670365","title":"Kitzbühler Alpen","price":679,"currency":"EUR","country":"Oostenrijk","departure":"","departureDate":"2027-01-11","duration":4,"stars":"4","province":"","region":"St Johann in Tirol","serviceType":"HP","url":"https://reis.tui.nl/c?c=433&m=1564650&a=453979&r=hackerdeal2.0&u=https%3A%2F%2Fwww.tui.nl%2Fkitzbuhler-alpen-509670365%2F%3FDepartureDate%3D2027-01-11%26Duration%3D4%26TransportType%3D2","banner":"https://media.tuicontent.nl/D51/D51DCCABAC02FF21818453A75ABCA83C.jpg"},{"id":"59260","title":"Grandhotel","price":682,"currency":"EUR","country":"Oostenrijk","departure":"","departureDate":"2027-03-15","duration":4,"stars":"4","province":"","region":"Salzburgerland","serviceType":"HP","url":"https://reis.tui.nl/c?c=433&m=1564650&a=453979&r=hackerdeal2.0&u=https%3A%2F%2Fwww.tui.nl%2Fgrandhotel-50959260%2F%3FDepartureDate%3D2027-03-15%26Duration%3D4%26TransportType%3D2","banner":"https://media.tuicontent.nl/240/240D570BDD5238E92897D817992C331C.jpg"},{"id":"984237","title":"Saalbach Suites by Alps Resorts","price":695,"currency":"EUR","country":"Oostenrijk","departure":"","departureDate":"2026-10-01","duration":4,"stars":"","province":"","region":"Saalbach Hinterglemm Leogang Fieberbrunn","serviceType":"LO","url":"https://reis.tui.nl/c?c=433&m=1564650&a=453979&r=hackerdeal2.0&u=https%3A%2F%2Fwww.tui.nl%2Fsaalbach-suites-by-alps-resorts-509984237%2F%3FDepartureDate%3D2026-10-01%26Duration%3D4%26TransportType%3D2","banner":"https://media.tuicontent.nl/B34/B34F86D2CAE4599CC17A27790D842BDE.jpg"},{"id":"24282","title":"Schutthof","price":696,"currency":"EUR","country":"Oostenrijk","departure":"","departureDate":"2027-01-09","duration":4,"stars":"3","province":"","region":"Salzburgerland","serviceType":"LO","url":"https://reis.tui.nl/c?c=433&m=1564650&a=453979&r=hackerdeal2.0&u=https%3A%2F%2Fwww.tui.nl%2Fschutthof-50924282%2F%3FDepartureDate%3D2027-01-09%26Duration%3D4%26TransportType%3D2","banner":"https://media.tuicontent.nl/AB4/AB49BFDF96AF198CBA10E4CEF5ED2DE2.jpg"}]