[{"id":"13096","title":"Tavistock","price":384,"currency":"EUR","country":"Verenigd Koninkrijk","departure":"","departureDate":"2026-06-15","duration":4,"stars":"3","province":"","region":"Engeland","serviceType":"LG","url":"https://reis.tui.nl/c?c=433&m=1564650&a=453979&r=hackerdeal2.0&u=https%3A%2F%2Fwww.tui.nl%2Ftavistock-50913096%2F%3FDepartureDate%3D2026-06-15%26Duration%3D4%26TransportType%3D2","banner":"https://media.tuicontent.nl/5A6/5A6711267E3CB802DCA44CD07F6F960B.jpg"},{"id":"723728","title":"Premier Inn Croydon Center","price":423,"currency":"EUR","country":"Verenigd Koninkrijk","departure":"","departureDate":"2026-06-23","duration":4,"stars":"3","province":"","region":"Engeland","serviceType":"LO","url":"https://reis.tui.nl/c?c=433&m=1564650&a=453979&r=hackerdeal2.0&u=https%3A%2F%2Fwww.tui.nl%2Fpremier-inn-croydon-center-509723728%2F%3FDepartureDate%3D2026-06-23%26Duration%3D4%26TransportType%3D2","banner":"https://media.tuicontent.nl/940/940EF986336AEADC320D8A8CA152D141.jpg"},{"id":"818931","title":"Four Points Flex by Sheraton Shoreditch East","price":458,"currency":"EUR","country":"Verenigd Koninkrijk","departure":"","departureDate":"2026-06-23","duration":4,"stars":"3","province":"","region":"Engeland","serviceType":"LG","url":"https://reis.tui.nl/c?c=433&m=1564650&a=453979&r=hackerdeal2.0&u=https%3A%2F%2Fwww.tui.nl%2Ffour-points-flex-by-sheraton-shoreditch-east-509818931%2F%3FDepartureDate%3D2026-06-23%26Duration%3D4%26TransportType%3D2","banner":"https://media.tuicontent.nl/CBE/CBE5135637E298E19EBF884F01F5E606.jpg"},{"id":"466226","title":"Columbia","price":470,"currency":"EUR","country":"Verenigd Koninkrijk","departure":"","departureDate":"2026-06-22","duration":4,"stars":"2","province":"","region":"Engeland","serviceType":"LG","url":"https://reis.tui.nl/c?c=433&m=1564650&a=453979&r=hackerdeal2.0&u=https%3A%2F%2Fwww.tui.nl%2Fcolumbia-509466226%2F%3FDepartureDate%3D2026-06-22%26Duration%3D4%26TransportType%3D2","banner":"https://media.tuicontent.nl/5B9/5B933200EA8EB0F34E8DDC744602CDCC.jpg"},{"id":"12653","title":"Thistle Bloomsbury Park","price":499,"currency":"EUR","country":"Verenigd Koninkrijk","departure":"","departureDate":"2026-06-22","duration":4,"stars":"3","province":"","region":"Engeland","serviceType":"LG","url":"https://reis.tui.nl/c?c=433&m=1564650&a=453979&r=hackerdeal2.0&u=https%3A%2F%2Fwww.tui.nl%2Fthistle-bloomsbury-park-50912653%2F%3FDepartureDate%3D2026-06-22%26Duration%3D4%26TransportType%3D2","banner":"https://media.tuicontent.nl/80E/80EB100A1B356CC21A26BD90397BAE91.jpg"},{"id":"801214","title":"Dao by Dorsett West London","price":500,"currency":"EUR","country":"Verenigd Koninkrijk","departure":"","departureDate":"2026-06-23","duration":4,"stars":"4","province":"","region":"Engeland","serviceType":"LG","url":"https://reis.tui.nl/c?c=433&m=1564650&a=453979&r=hackerdeal2.0&u=https%3A%2F%2Fwww.tui.nl%2Fdao-by-dorsett-west-london-509801214%2F%3FDepartureDate%3D2026-06-23%26Duration%3D4%26TransportType%3D2","banner":"https://media.tuicontent.nl/6E2/6E2962B64071EF905662B2F686682B1D.jpg"},{"id":"647881","title":"Moxy London Excel","price":536,"currency":"EUR","country":"Verenigd Koninkrijk","departure":"","departureDate":"2026-06-08","duration":4,"stars":"3","province":"","region":"Engeland","serviceType":"LG","url":"https://reis.tui.nl/c?c=433&m=1564650&a=453979&r=hackerdeal2.0&u=https%3A%2F%2Fwww.tui.nl%2Fmoxy-london-excel-509647881%2F%3FDepartureDate%3D2026-06-08%26Duration%3D4%26TransportType%3D2","banner":"https://media.tuicontent.nl/48A/48A00C8439AC6361E3EE236AB0FE155D.jpg"},{"id":"982849","title":"Mercure London Earls Court","price":584,"currency":"EUR","country":"Verenigd Koninkrijk","departure":"","departureDate":"2026-06-23","duration":4,"stars":"4","province":"","region":"Engeland","serviceType":"LG","url":"https://reis.tui.nl/c?c=433&m=1564650&a=453979&r=hackerdeal2.0&u=https%3A%2F%2Fwww.tui.nl%2Fmercure-london-earls-court-509982849%2F%3FDepartureDate%3D2026-06-23%26Duration%3D4%26TransportType%3D2","banner":"https://media.tuicontent.nl/FCB/FCBC40520E55E3170689497FE8266BFE.jpg"},{"id":"801249","title":"Tribe London Canary Wharf","price":598,"currency":"EUR","country":"Verenigd Koninkrijk","departure":"","departureDate":"2026-06-23","duration":4,"stars":"4","province":"","region":"Engeland","serviceType":"LG","url":"https://reis.tui.nl/c?c=433&m=1564650&a=453979&r=hackerdeal2.0&u=https%3A%2F%2Fwww.tui.nl%2Ftribe-london-canary-wharf-509801249%2F%3FDepartureDate%3D2026-06-23%26Duration%3D4%26TransportType%3D2","banner":"https://media.tuicontent.nl/00F/00FCE3F725BBB0A9BDC0DA3E3F8E6F62.jpg"},{"id":"803139","title":"Wilde London Paddington","price":601,"currency":"EUR","country":"Verenigd Koninkrijk","departure":"","departureDate":"2026-06-23","duration":4,"stars":"4","province":"","region":"Engeland","serviceType":"LG","url":"https://reis.tui.nl/c?c=433&m=1564650&a=453979&r=hackerdeal2.0&u=https%3A%2F%2Fwww.tui.nl%2Fwilde-london-paddington-509803139%2F%3FDepartureDate%3D2026-06-23%26Duration%3D4%26TransportType%3D2","banner":"https://media.tuicontent.nl/6ED/6ED745C04DD9F80CE49E5B0BD92A3C7B.jpg"},{"id":"802352","title":"Yotel London City","price":662,"currency":"EUR","country":"Verenigd Koninkrijk","departure":"","departureDate":"2026-06-23","duration":4,"stars":"4","province":"","region":"Engeland","serviceType":"LG","url":"https://reis.tui.nl/c?c=433&m=1564650&a=453979&r=hackerdeal2.0&u=https%3A%2F%2Fwww.tui.nl%2Fyotel-london-city-509802352%2F%3FDepartureDate%3D2026-06-23%26Duration%3D4%26TransportType%3D2","banner":"https://media.tuicontent.nl/ADB/ADBF57E0F91AFBB55CC3D684CFFE51CF.jpg"},{"id":"669581","title":"Ibis Edinburgh Centre South Bridge","price":673,"currency":"EUR","country":"Verenigd Koninkrijk","departure":"","departureDate":"2026-06-21","duration":4,"stars":"3","province":"","region":"Schotland","serviceType":"LO","url":"https://reis.tui.nl/c?c=433&m=1564650&a=453979&r=hackerdeal2.0&u=https%3A%2F%2Fwww.tui.nl%2Fibis-edinburgh-centre-south-bridge-509669581%2F%3FDepartureDate%3D2026-06-21%26Duration%3D4%26TransportType%3D2","banner":"https://media.tuicontent.nl/BB4/BB4B9399F4878EDC055930E3721CBFB2.jpg"},{"id":"612334","title":"Novotel London Canary Wharf","price":689,"currency":"EUR","country":"Verenigd Koninkrijk","departure":"","departureDate":"2026-06-22","duration":4,"stars":"4","province":"","region":"Engeland","serviceType":"LG","url":"https://reis.tui.nl/c?c=433&m=1564650&a=453979&r=hackerdeal2.0&u=https%3A%2F%2Fwww.tui.nl%2Fnovotel-london-canary-wharf-509612334%2F%3FDepartureDate%3D2026-06-22%26Duration%3D4%26TransportType%3D2","banner":"https://media.tuicontent.nl/C32/C32C742589426A464C18C3A8F51F69BF.jpg"}]